onedice/__init__.py
onedice/main.py
onedice-1.0.7.dist-info/METADATA
onedice-1.0.7.dist-info/WHEEL
onedice-1.0.7.dist-info/top_level.txt
onedice-1.0.7.dist-info/RECORD
