Metadata-Version: 2.1
Name: onedice
Version: 1.0.7
Summary: OneDice offical standard library for Python
Home-page: https://github.com/OlivOS-Team/lib-onedice
Author: lunzhiPenxil
Author-email: lunzhiPenxil@gmail.com
Classifier: Programming Language :: Python :: 3
Classifier: License :: OSI Approved :: GNU Affero General Public License v3
Classifier: Operating System :: OS Independent
